aind_behavior_gym/__init__.py
aind_behavior_gym/dynamic_foraging/__init__.py
aind_behavior_gym/dynamic_foraging/agent/__init__.py
aind_behavior_gym/dynamic_foraging/agent/base.py
aind_behavior_gym/dynamic_foraging/agent/random_agent.py
aind_behavior_gym/dynamic_foraging/task/__init__.py
aind_behavior_gym/dynamic_foraging/task/base.py
aind_behavior_gym/dynamic_foraging/task/coupled_block_task.py
aind_behavior_gym/dynamic_foraging/task/random_walk_task.py
aind_behavior_gym/dynamic_foraging/task/uncoupled_block_task.py
aind_behavior_gym-0.4.3.dist-info/LICENSE
aind_behavior_gym-0.4.3.dist-info/METADATA
aind_behavior_gym-0.4.3.dist-info/WHEEL
aind_behavior_gym-0.4.3.dist-info/top_level.txt
aind_behavior_gym-0.4.3.dist-info/RECORD
